ABSTRACT.txt
ChangeLog.txt
MANIFEST.in
README.rst
setup.py
metameta/__init__.py
metameta.egg-info/PKG-INFO
metameta.egg-info/SOURCES.txt
metameta.egg-info/dependency_links.txt
metameta.egg-info/entry_points.txt
metameta.egg-info/not-zip-safe
metameta.egg-info/requires.txt
metameta.egg-info/top_level.txt
metameta/bin/__init__.py
metameta/bin/__main__.py
metameta/bin/count_objects.py
metameta/bin/generate_fastr.py
metameta/data/Documentation.txt
metameta/data/__init__.py
metameta/metameta_utils/__init__.py
metameta/metameta_utils/fastr_utils.py
metameta/metameta_utils/output.py