Metadata-Version: 1.1
Name: metameta
Version: 0.0.0.66
Summary: Toolkit for analyzing meta-transcriptome/metagenome mapping data
Home-page: https://github.com/Brazelton-Lab/metameta/
Author: Alex Hyer
Author-email: theonehyer@gmail.com
License: GPL
Download-URL: https://github.com/Brazelton-Lab/metameta/tarball/0.0.0.66
Keywords: bioinformatics metadata metagenome metatranscriptomeshort reads mapping alignment
Platform: UNKNOWN
Classifier: Development Status :: 7 - Inactive
Classifier: Intended Audience :: Science/Research
Classifier: License :: OSI Approved :: GNU General Public License v2 (GPLv2)
Classifier: Natural Language :: English
Classifier: Operating System :: OS Independent
Classifier: Programming Language :: Python :: 3.4
Classifier: Topic :: Scientific/Engineering :: Bio-Informatics
